create_command
scrapy_redis_frame
