Metadata-Version: 2.1
Name: scrapy-redis-frame
Version: 1.0.4
Summary: Scrapy Redis Util Package
Home-page: UNKNOWN
Author: SilenceSmile
Author-email: 845666796@qq.com
License: UNKNOWN
Platform: UNKNOWN
Classifier: Programming Language :: Python :: 3
Classifier: License :: OSI Approved :: MIT License
Classifier: Operating System :: OS Independent
